saxoncpe.cpython-312-x86_64-linux-gnu.so
cpp/include/CythonExceptionHandler.h
saxonc/saxonc.cpp
saxoncpe.libs/libsaxonc-core-pe-96e71281.so.12.9.0
saxoncpe.libs/libsaxonc-pe-e58689b0.so.12.9.0
saxoncpe-12.9.0.dist-info/METADATA
saxoncpe-12.9.0.dist-info/WHEEL
saxoncpe-12.9.0.dist-info/top_level.txt
saxoncpe-12.9.0.dist-info/RECORD
