Metadata-Version: 2.4
Name: saxoncpe
Version: 12.9.0
Summary: Official Saxonica python package for the SaxonC-PE 12.9.0 processor: for XSLT 3.0, XQuery 3.1, XPath 3.1 and XML Schema processing.
Author-email: ONeil Delpratt <oneil@saxonica.com>, Matt Patterson <matt@saxonica.com>
Project-URL: Homepage, https://www.saxonica.com/saxon-c/index.xml
Project-URL: Documentation, https://www.saxonica.com/saxon-c/documentation12/index.html
Project-URL: Issues, https://saxonica.plan.io/projects/saxon-c
Requires-Python: >=3.9
